{"ZuvE6Urn+A9mMpO00aeupg==":"mbr-1920x1079.jpg","ro405pA40dxTuifOARlSAA==":"shutterstock-408019909-2000x1335.jpg","OM6hTwqMAQpTVhLcPG86xg==":"background1.jpg","pa5Dkwo/T1qgW/t0h+fQvA==":"background5.jpg","X3HdyO26xjrTEKfE7rt+AQ==":"screen%20shot%202019-04-15%20at%202.08.26%20pm-1204x1051.png","wF1HORX+uuilbD7Huvm+Cw==":"mbr-676x451.jpg","rkvcPYkyMGQfpfC1yC7kZg==":"mbr-676x449.jpg","HXql50COh9RcvOYdT3kRRw==":"mbr-1-676x451.jpg","SwzDRVAVNV/YGRUu1U/03g==":"kristof%20de%20spiegeleer-314x314.jpg","QVyumce63ge2Y2Vzl1uogA==":"adnan_fatayerji-250x250.jpg","AmpZV3BzWt6lvEE3R8yk9g==":"chris_hutton_processed-250x250.jpg","qhC1WvRdtF0p2wQAAggyWw==":"tf-bg-2-2000x1125.jpg","j+16SbQTKrU28xVnfDw9jg==":"owen_kemp_processed-250x250.jpg","NKU15K4mVmMX3IMx2AZ3Yw==":"weynand_kuijpers_processed-250x250.jpg","5DLzPu2sUewK9TnxcqA8HQ==":"andreas_hartl_processed-250x250.jpg","U4AH+JkoGaL2mtkFa3o8nQ==":"manymore-245x205.png","NTj0F532ifEtJYcNLHRovA==":"manymore-1-245x205.png","W+hIVlOjUkUwZSMiqKHwnQ==":"manymore-2-245x205.png","Bz/rdi7LFdx+FKYznyI/HQ==":"screenshot%202019-06-01%20at%2023.04.55-1204x480.png","MBGkxHx95i/HEQx6b9WzZw==":"screenshot%202019-06-01%20at%2023.04.55-1204x480.png","W6uO38/Y5rp4PifRydBecg==":"mbr-1920x1344.jpg","bliJBSpcMC/MJWrSQsivKA==":"mbr-1920x1177.jpg","x2oS2k4uTOyHMhI9pcOjjg==":"mbr-1920x1113.jpg","vJ4/XSpRZ/eBiwbonCd3vA==":"kal-visuals-644747-unsplash-952x1428.jpg","UaK0/IJtggX/cjhCyT+eww==":"mbr-952x635.jpg","YMAEkGIcJAt+leWQxnVvuw==":"mbr-1-952x635.jpg","zNdTfiFoodZg8X5Z6ocJ5g==":"boudewijn-huysmans-705525-unsplash-2000x1317.jpg","3rwJLd0/ONNXRL0ahKNZlw==":"mikhail-vasilyev-235560-unsplash-2000x1333.jpg","l7FsQkuDULqoiPxuWY5hyQ==":"stop%20climate%20change-800x800.png","e7vXPs8TtRQcJWKBRYD8JQ==":"stop%20climate%20change%20(1)-522x522.png","vTURRFSfKKXXbq0dEn/U8Q==":"for%20every%20negative,%20there%20is%20a%20positive-632x632.png","NjgUf+zQt79peGM5OrmQYw==":"for%20every%20negative,%20there%20is%20a%20positive-632x632.png","I2KaSuE+7dbQG/vAetA8VQ==":"doug-linstedt-135670-unsplash-2000x1125.jpg","YrDT+Jxf0TF6c5rs7FUTeA==":"ato-aikins-283964-unsplash-556x417.jpg","KDf/FJnWVHxMnsOvhB+VNw==":"mbr-2-676x451.jpg","vP2BmLyDZjjHXYxxbLRvXg==":"ato-aikins-283964-unsplash-1-556x417.jpg","giBqJYdHqkYVraC0GsHSAg==":"jeremy-bishop-74121-unsplash-556x371.jpg","LIsrFoitLV2WMqmIdMOYzQ==":"markus-spiske-482453-unsplash-556x834.jpg","YbPoH4v7qImx4cvIj1k4RA==":"schermafbeelding%202019-06-04%20om%2010.55.52-240x240.png","Nxlj3mKMbARqK/VcbWqrlA==":"jennifer-240x240.jpg","7WPVRjoJdGDzi03C1LNRXw==":"mike-240x240.jpg","NlUZzF428oifx2Qrskwx5w==":"nanapoku-784859-unsplash-952x1428.jpg","bKf3BHgc7WJ6j5WCvex1Qg==":"nanapoku-784859-unsplash-1-952x1428.jpg","VWwyosGdgY7JZbKwEX7UeA==":"deforest-525x720.jpg","uT/Y7qMvCMi0J1tqzBCSXA==":"screen%20shot%202019-06-13%20at%2012.36.20%20pm-952x534.png","S/WLnZQnNXFi6sEpKb8euA==":"rainforest%20slider%20image%20-1600x900.jpg","lQuSo1iQWEGiDiZWX5+A2g==":"arran-smith-408953-unsplash-2000x1333.jpg","uy/wHLP5ol2FroK2y1I08w==":"robin-worrall-749755-unsplash-2000x1333.jpg","UOXL0W4nUnYyMuYaGRQ3Jg==":"anastasia-dulgier-1156050-unsplash-2000x1250.jpg","4QH7u/5uen8d1TRqb/fbWw==":"nischal-masand-270164-unsplash-2000x1123.jpg","HJpSOAjd1CTMQctOxH0aVw==":"sergio-souza-796530-unsplash-952x903.jpg","WRLhgHrWnn1TMZdxU3K5vA==":"sergio-souza-796530-unsplash-1-952x903.jpg","MADR/ToRH4XLWaBhnF7WXA==":"sergio-souza-796530-unsplash-2-952x903.jpg","tP2tAPYYNyXr8jHy5uHNAQ==":"sergio-souza-796530-unsplash-3-952x903.jpg","kWg3q3TsQhqoMHcLdz0P4Q==":"host-sorter-1479500-unsplash-676x424.jpg","n5S0hYEgRDzPlGf7wc8RRg==":"host-sorter-1479500-unsplash-1-676x424.jpg","QBnpXvJMxhdVpseXHFs56Q==":"nanapoku-784859-unsplash-682x1023.jpg","moDDgrmUJJ9iimJaSUASIA==":"photo_2019-06-13%2017.43.11-240x240.jpg","67G0eN5hiQgSg9OH04Adxw==":"photo_2019-06-13%2017.44.09-240x240.jpg","7ejYTi5QKaIGGZ/Pkd3gOQ==":"photo_2019-06-13%2017.44.33-240x240.jpg","PbfRJ+bih85Y9ITmxHrZ9Q==":"isabella-juskova-258910-unsplash-592x395.jpg","gis6flx/ktvdTOPWFo3GXg==":"jazmin-quaynor-1592302-unsplash-592x791.jpg","nXj6QMdMXTG69JU05kqahw==":"waterfall%20view%20from%20cabins%20-2000x1125.jpg","UoO42kttg08hfcCcs8EU4g==":"sergio-souza-796530-unsplash-772x733.jpg","MT5+NgrcvIU5RniT4iB1EQ==":"sergio-souza-796530-unsplash-1-772x733.jpg","uI9CPlq4RrkdVBty0Q25Jg==":"sergio-souza-796530-unsplash-2-772x733.jpg","JlnkAAmou+KdjqSDS+M6Pg==":"nanapoku-784859-unsplash-772x1158.jpg","KvItiRnI8rkIHWiUrcr4yA==":"schermafbeelding-2019-06-04-om-10.55.52-1-240x240.png","kb+0JzO980gCNxEo89f+CQ==":"jennifer-1-240x240.jpg","VsPTz+IUiz2+j3FDwkSfcg==":"mike-1-240x240.jpg","ExtbBE1m7jNE+VrBrHBgxA==":"sergio-souza-796530-unsplash-3-772x733.jpg","qpd/oB4Slrw99QxqhqXv8w==":"nanapoku-784859-unsplash-1-772x1158.jpg","gpfFX3mBWDf0DsIhEkzBMw==":"rohan-makhecha-408608-unsplash-556x834.jpg","tTjHDy0x9rRHxfFYDYMzOQ==":"avel-chuklanov-38687-unsplash-556x371.jpg","mbxgfzA3q3x4A/Yx6/j7ww==":"rohan-makhecha-408608-unsplash-1-556x834.jpg","A/J1jIDsoofTcG3wahrpkg==":"jonathan-larson-1590592-unsplash-556x376.jpg","gev87850bpj05Lkt+uGecw==":"rohan-makhecha-408608-unsplash-2-556x834.jpg","hGaT0TUi5hWdDv7xVk9/mA==":"adrianna-van-groningen-1454998-unsplash-556x371.jpg","1/FF5lcSaGQbO0N1QDW70A==":"adrianna-van-groningen-1454998-unsplash-1-556x371.jpg","odftpU3vEt5lQ2l4Tokj6Q==":"rod-long-787232-unsplash-2000x1333.jpg","UAc7kepzJPkrSn4uqTRvmw==":"background4-1.jpg","4ppDNCWKlaJHorRJMDq+Hw==":"20181213_13-33-3420181213-93996-510x764.jpg","B6+xqBYzP/3g4eRq0hukjQ==":"20181214_08-34-0220181214-94236-510x764.jpg","Q6GJQpoQTncFGbS53I7bng==":"photo_2019-06-28%2012.29.10-510x764.jpg","0x6AxPDyUiwZTamVSPLiSA==":"20190522_20-35-4920190522-100753-510x764.jpg","qD57f/h4vOeD8zy4jkhvXQ==":"20190522_20-35-4920190522-100754-510x764.jpg","6MXtLMVsTHz3pF3RixZliw==":"20190522_20-35-4920190522-100755-510x764.jpg","hiRnTAR/lf49dZZcupGHNg==":"20190525_17-46-5920190525-102065-510x764.jpg","d7gQkxCltBQz8YjAJGxgNw==":"20190526_19-10-0220190526-101721-510x764.jpg","GsghX0MVhfkC7eF9jxkFJw==":"photo_2019-06-28%2008.48.00-510x319.jpg","DvoSQ6pRutoWAFPQwwlOPA==":"photo_2019-06-28%2008.48.00-510x319.jpg","fiO+hWyUMWZTOg7yJWwWpA==":"20190525_17-11-5520190525-102033-510x764.jpg","8vXdcFeZQ7URWA3+qpBmdA==":"20181215_14-43-1920181215-95112-510x764.jpg","1eR++BurXwrFX3/Ct2JZgQ==":"20181213_13-33-3420181213-93996-412x617.jpg","MmlBs2BfGSFrfA9yCQjbmg==":"20181215_14-43-1920181215-95112-412x617.jpg","fCPnNttVZyD7ZM9PVgwfSg==":"photo_2019-06-28%2012.29.10-412x618.jpg","m2N0zWwrzMA0YHa3aAV2sw==":"20190525_17-11-5520190525-102033-412x617.jpg","hUsVcUlmEXW/fu79wetmnA==":"20190522_20-35-4920190522-100753-412x617.jpg","Hk9A+/LqZAcmIxdjQv7ikA==":"20190525_17-46-5920190525-102065-412x617.jpg","S6d8bv07fQFFV3+LJHOXeg==":"unnamed-412x515.jpg","fb4M0Hlu+UIHbgPtSv+xLw==":"clement%20threefold-952x1427.jpg","npc+LghYudP7mNJJsVtd+A==":"luis-quintero-ibwxfqoept4-unsplash-2000x1333.jpg","ijfpNTMdqDgmYVXJkV6SZw==":"matheus-ferrero-37iplzyz-r4-unsplash-2000x3001.jpg","7hF8KkDGtxpzYu32Vqlc7w==":"matheus-ferrero-37iplzyz-r4-unsplash-1-2000x3001.jpg","cm/pdNRraKnc25H2KU8duw==":"matheus-ferrero-37iplzyz-r4-unsplash-2-2000x3001.jpg","1CW4918EiWume/5YuSe4cw==":"matheus-ferrero-37iplzyz-r4-unsplash-3-2000x3001.jpg","a/BaFKiwSB7CC406EGig4g==":"background6.jpg","z6ZfLgd9OBzf8K4H4ABlWw==":"background7.jpg","mIIbxW0r7dEZSbMPwcoYdg==":"background2.jpg","r2Y66uxYMcc1PRk9NnbjBQ==":"sarah-dorweiler-9z1krifpbtm-unsplash-2000x1333.jpg","slhjfdqTtr0R6WGNp0xDWA==":"photo_2019-06-28%2008.47.44-1280x800.jpg","9TbZ1nBv3jXTqJAICbxHhA==":"egypte%20veda%20(243%20van%20577)-2490x1556.jpg","/2hVunsTikqVVr0lzj1A4Q==":"egypte%20veda%20(243%20van%20577)-2490x1556.jpg","wZI8XgY3uoAjr/vQozWN+w==":"clement-threefold-1-952x1427.jpg","gUnv9ie1QQvTfoveABsgtg==":"photo_2019-06-28%2008.48.00-1280x800.jpg","GA+FrEZKqq0Asgdxe5J+4g==":"20190523_11-16-5320190523-100908-2490x3730.jpg","cKlCzheT1cE0GbSyk1fwtQ==":"20190523_11-16-5320190523-100909-2490x3730.jpg","6VZnPhDVQjrfZ6KdtnzKCg==":"20181214_09-22-2420181214-94295-2490x3730.jpg","OjIhpSR2Yn1nf4qSmjG70g==":"20190525_16-40-5420190525-102017-2490x3730.jpg","fRbawMcEVE8gtMTD/Zy3hg==":"20181214_09-22-2420181214-94295-422x632.jpg","svjCL2BI0BaLU0nWzhCscg==":"federico-beccari-ahi73zn5p0y-unsplash-676x451.jpg","rtr4v0JYjHa9WNLeU7KWOw==":"nikhita-s-nspdipftp4c-unsplash-676x451.jpg","CVATxr0TRi3LHwfFDJ2Rfg==":"josh-appel-qsipy5rfcsa-unsplash-676x900.jpg","2KlwAxgsAnf0yoPKUohcjg==":"josh-appel-qsipy5rfcsa-unsplash-1-676x900.jpg","TPxHcu1PTDYHyfrFZeM0Aw==":"fabian-blank-pelskgra2nu-unsplash-676x451.jpg","IcgLuvhi/IiSWgwyQPZaOg==":"bernard-hermant-bbutpy447ga-unsplash-676x451.jpg","sT80Y4RCGNBrSInGgrjIuA==":"background3.jpg","uEGrZzKM+GOqz2luW5pm/A==":"adrianna-van-groningen-nvd9zz7nn8q-unsplash-676x451.jpg","Kgkk1vSXp+7nZnB3Hk7z1A==":"neonbrand-zfso6bnzjtw-unsplash-676x421.jpg","4LuvjnoIYEaj5XkkMcSHDw==":"wassim-mechergui-hyhs-fecjbm-unsplash-676x451.jpg","6IwRkFEC9rmCl73NgkVF6Q==":"nasa-q1p7bh3shj8-unsplash%20(1)-676x450.jpg","qBvs4K5O4Uby+alOzQ1+Tg==":"adrianna-van-groningen-nvd9zz7nn8q-unsplash-1-676x451.jpg","SxnVEYn2pSfv+TaI8qG7iw==":"neonbrand-zfso6bnzjtw-unsplash-1-676x421.jpg","A9FWdm+cMy8P+dkXuXHS+A==":"wassim-mechergui-hyhs-fecjbm-unsplash-1-676x451.jpg","4DwQgOwmAtEIDU6fuutp/g==":"nasa-q1p7bh3shj8-unsplash-2-676x450.jpg","qVPyD/fUCrpfy5r/Nf94Xg==":"hal-gatewood-ogvqxgl7xo4-unsplash-676x451.jpg","Dxt50c19reSv/gfQ/FQ5MQ==":"riccardo-annandale-7e2pe9wjl9m-unsplash-676x542.jpg","7g7n+W78SbLjJLMlhP2oNQ==":"hal-gatewood-ogvqxgl7xo4-unsplash-1-676x451.jpg","qht94nz2Te1SU+NPPlEqyQ==":"nasa-q1p7bh3shj8-unsplash%20(1)-676x450.jpg","sUquDuBbF5JTZJ3/3lKQCg==":"jack-t-6p3azeuetfu-unsplash-676x451.jpg","FAirDaRHUAk8mMbBjtJgKg==":"nick-dietrich-pvrgto_wbry-unsplash-676x1036.jpg","OG73nUCyQEvzGjRZs9MGug==":"isabella-juskova-xotmnyn3gdc-unsplash-676x451.jpg","gFsoxPCM4W+fK7Cuguurjg==":"ibrahim-rifath-oaphds2yegq-unsplash-676x451.jpg","FGrRxvJCn7Z7yBLPyEv46Q==":"20190525_14-23-2520190525-101458-436x653.jpg","mHRFMEJDp9F5DmfGoYhI8A==":"screen%20shot%202019-06-26%20at%204.33.44%20pm-1104x796.png","+l4UqtzKFExh9E01h0jxjQ==":"20190525_20-56-0320190525-102175%20(1)-2560x3835.jpg","45NDadphnyaGn56NLiaPYA==":"photo-2019-06-28-08.48.00-1-1280x800.jpg","hpVBV5HGw3p8d6ME/dudVw==":"freeflow-color-2-300x60.png","Tj5aBK7fe0dYwKFsomr/Gg==":"trinity-treft-k86_ynmipw0-unsplash-436x291.jpg","YkEa3LALiksHHSShUorB+g==":"bob-blob-ycw4yxhrwhm-unsplash-2000x1333.jpg","Zs2B6UlTWsdpbI6B3x57Ow==":"22883580_1481280538635657_167321911_ob-640x640.png","xVKeFhCT5TZp275aXAyl+g==":"22688570_1713318285405217_6129377349620487607_n-491x811.jpg","VBOV8qIIseg5EudNbHaXtw==":"22688570_1713318285405217_6129377349620487607_n-1-491x811.jpg","jcxRaCP8u+zBV6iG23Z1tA==":"img_8440-683x1024@2x-240x360.jpg","QoVjN71BSgGAHNi7EAKeJg==":"alfred-hofer-foto.256x256-240x240.jpg","UbU+gIpM1trWQZGY5oS2Bw==":"andrew-stutesman-l68z6ef2pea-unsplash-2000x1329.jpg","t2njqQLpkyc5T+q/r41bWg==":"joshua-sortino-lqkhndzsf-8-unsplash-2000x1336.jpg","P1lPi3qv8qVNEVbWdzj9Vg==":"doug-linstedt-135670-unsplash-1-2000x1125.jpg","zNmdX2PKQx0PIBcWSUFlsQ==":"bob-blob-ycw4yxhrwhm-unsplash-1-2000x1333.jpg","MgYHjw50mcnO5bwdLrQXBg==":"andrew-stutesman-l68z6ef2pea-unsplash-1-2000x1329.jpg","jbGSpG0c5lCEuSRTihZvqg==":"photo_2019-08-10%2017.52.27-1280x960.jpg","vQ4s9wJdhPB7TjWLzx5whA==":"photo_2020-01-02%2012.09.33-1280x853.jpg","sNSOQr1y9CPpKqvyJhfFbw==":"photo_2020-01-02%2012.16.04-420x560.jpeg","1JZ3es+Il7BFO4BGrzXpXg==":"photo_2020-01-02%2012.16.04-420x560.jpeg","yu1Ov3fq2DI2cegQzY82+Q==":"60880966_10216566823822037_6526844208098050048_n-420x420.jpg","FxHVG0CVgP/F7JHP8qyd3Q==":"face2-1.jpg","fQ2oEZGBjc7C9iYOXn1pSw==":"face3-1.jpg","LV2FDVpWb6HqC+Hgx8jtLQ==":"face3.jpeg","Zzdu+3KPBMo3i7W+2kQZRw==":"olivia-510x510.jpg","dfVbztdhqk7uAlredaLHQQ==":"adnan-510x510.jpg","sv3JxqmV8TAYKBLU839EEg==":"sabrina-510x510.jpg","sd/fQ6vzKMv/2HUKi1modw==":"zidan-510x682.jpeg","ZmK8kR05rBFfhSkneY2GyQ==":"ahmed-510x680.jpeg","G9/bCsOvSL3yAb4hh5gFTg==":"screenshot%202020-01-16%20at%2011.07.32-510x642.png","AzYImYAzj8pDIPMw1sqC3Q==":"simin-354x532.jpeg","WfHvn+SyTyHA8KcVdK3Wqg==":"reem-250x250.jpg","C0FX1MjjXQhRkqOW88SO6Q==":"andreas-510x340.jpeg","LbDmoTvmWKr5stVv2zCgMQ==":"weynand-250x250.jpg","NKVJeRzZG2oY/eK1Xy1q9Q==":"kristof_de_spiegeleer_processed-252x252.jpg","/2sajmxmVQPN78cLtIEXJQ==":"isabelle_peeters_processed-252x252.jpg","OfX+bj6wpan/mvwVJjCO8A==":"olivia_jurado_processed-252x252.jpg","EuzfLnM6jiHYk+QLpoxaAg==":"sam_taggart_processed-250x250.jpg","Sh+rATwMogKUWxg11Akgxg==":"sabrina_sadik_processed-250x250.jpg","aEIlc9zwKWzqafEJmnYgtA==":"sacha_oobeegado_processed-250x250.jpg","bY2ZZa1EYDHObYO/ypclZg==":"simin_gerards_processed-252x252.jpg","s8bYzOHaIpTOu62lJwnUxQ==":"face2.jpeg","/5TxP6rB5Xsj6wML99MSww==":"logo4.png","0HERTd0uKh4KAh61FdjSCw==":"ahmed%20copy-461x461.jpg","J+bjCeuwYRyjY2AtqH9bmw==":"ahmed%20copy-461x461.jpeg","dlEi/bbVBDwE+1W0aAOBGg==":"0-200x200.jpg","gtj2iJ4+uNkq4p3v0uZwNA==":"michael%20ww-510x1104.png","W9bnuGhWpODAod3I11sOIA==":"0-1-200x200.jpg","FfN1hRkexpWjZULLqBoNBw==":"patrick%20team-300x300.jpg","CxL6UB+yCfI4uNncxSBiPw==":"0-2-200x200.jpg","j2KsEk7mQ7i2VRIMTcUY0g==":"0%20(1)-200x200.jpg","9tImT4OvaHT6Ih8HA3y5zw==":"0-3-200x200.jpg","UCGjZ4BrwIfZYihZ19JSBw==":"0%20(1)-200x200.jpg","MSEWJZmoEI+BSppfG556QA==":"2020-01-16%2021.37.31-510x510.jpg","V/25GhsjsQsahqQ1YaQXUA==":"0-4-200x200.jpg","7SsHqk7chB+/MnD8iwgoBA==":"michael%20ww-510x646.png","FybY5sdr41D9XefIzWPvmg==":"michael%20ww-510x553.png","4Ppd9eoQMB0DLrpEf4IN5g==":"michael%20ww-510x525.png","a/e4/T+ECClZR6LAi1P0DQ==":"0%20(1)-200x200.jpeg","MfsX50hdpLoSGDjopGLtEw==":"0-180x180.jpg","B4DzQnFOtirfx6RUrQRa2Q==":"mariza_kain-250x250.png","iM78++5H0BaMbjaZho5ugA==":"jennifer_long_processed-252x252.jpg","+3zO7+RT8G+7oOJ64m0PkA==":"michel_coucke_processed-252x252.jpg","U1TbsjfX4I43OXfbVblavQ==":"0%20(1)-200x200.jpeg","0aGaUDWrCM1X4PAGDm54fg==":"0%20(1)-200x200.jpeg","zkzYmKCEoSbw/y2Z2qatRg==":"0%20(1)-200x200.jpeg","Li6tOOykDxmkd+x9T3K3tw==":"lltes-20200110-510x664.jpeg","k181htGo5Bx2wDKJnePmhw==":"lltes-20200111-510x664.jpeg","1lCwwUExYzZ7MzicLDfhQg==":"screenshot%202020-01-17%20at%2008.09.22-482x596.png","J51TVpnkzS4lez/Aaq11Xw==":"screenshot%202020-01-17%20at%2008.09.22-482x596.png","mQotNkEqima1er0/QotV/g==":"screenshot%202020-01-17%20at%2008.11.52-510x427.png","VIHPx2TtMZb2e593Xv0zDA==":"isabelle-510x456.png","z3+7+gIB9eL9PtJiCOZMQg==":"isabelle-1-510x456.png","FbIlAwe/pFvQv27Q+qPeOg==":"michel%20bauwens-510x729.jpeg","Mp+UH6/WxbXfEJpAUKHzwQ==":"alain-259x194.jpeg","uK5ZIDNRrLcm+J9OKRnuAA==":"mariza-510x510.jpg","GwmGMcc4bdktBKX/58L6ng==":"jennifer-510x510.jpeg","AC1i7ru2odWHn8q9HUNbHw==":"adnan2-510x340.jpeg","pp6W6PNKJ2/dpmsOPE3RsQ==":"weynand-250x250.jpeg","E04M4tFJ9LehBLqR6YIa6w==":"sam-510x510.jpeg","maQToJl2fEnfGfdd8laCeQ==":"sabrina-1-510x510.jpg","d8B4TOs10tfhnS7VvjXpFA==":"sabrina-1-510x510.jpeg","WPFStk2owjiiZBGwL1F5Pw==":"ahmed-408x408.jpg","AoQEcN9lkLmKd6ZfHCA1RA==":"olivia-1-510x510.jpg","zGMkHfCW1vKiFp5BG8uCAQ==":"andreas-1-510x340.jpeg","uz8ZAptyrWoLtrBAoK337A==":"sacha-510x509.jpeg","vOK3FD79vMI8Qeh8fWUDlw==":"kristof-510x765.jpeg","OKR4z+L4RZAl4916ZzOFlA==":"gino-400x400.jpg","fqesj9o6dR6UO/isGzRobQ==":"shane%20williams-510x510.jpg","EONf+P5K2Hda3masDD3/pA==":"sacha-510x729.jpeg","IRQnhfNPmqQv9fV5O/c5Sw==":"shaun-500x500.jpg","wxxXMJ4agiG7Qcp156ACHQ==":"20190525-17-11-5520190525-102033-412x617.jpeg"}